LicenseVendor/__init__.py
LicenseVendor/app.py
LicenseVendor-1.0.1.dist-info/LICENSE
LicenseVendor-1.0.1.dist-info/METADATA
LicenseVendor-1.0.1.dist-info/WHEEL
LicenseVendor-1.0.1.dist-info/top_level.txt
LicenseVendor-1.0.1.dist-info/RECORD
